{"class": "go.GraphLinksModel", "nodeDataArray": [{"category": "Task", "text": "How to Hide Wall Posts from Others on Facebook", "fill": "#ffffff", "stroke": "#000000", "strokeWidth": 1, "key": -1, "refs": [], "ctsx": [], "comment": null}, {"category": "Task", "text": "Type what you want to write on the status text box.", "fill": "#ffffff", "stroke": "#000000", "strokeWidth": 1, "key": -2, "refs": [], "ctsx": [], "comment": "null"}, {"category": "Task", "text": "Now click on the privacy icon and look at the options - Public, Only Me and Custom.", "fill": "#ffffff", "stroke": "#000000", "strokeWidth": 1, "key": -3, "refs": [], "ctsx": [], "comment": "null"}, {"category": "Task", "text": "Now, this box will come up.", "fill": "#ffffff", "stroke": "#000000", "strokeWidth": 1, "key": -4, "refs": [], "ctsx": [], "comment": "null"}, {"category": "Task", "text": "If you want to hide this post from a particular person, enter his/her/their names.", "fill": "#ffffff", "stroke": "#000000", "strokeWidth": 1, "key": -5, "refs": [], "ctsx": [], "comment": "null"}, {"category": "Task", "text": "Click on \"Save Changes\".", "fill": "#ffffff", "stroke": "#000000", "strokeWidth": 1, "key": -6, "refs": [], "ctsx": [], "comment": "null"}, {"category": "Task", "text": "Check if you have hid the post already, hover over your privacy icon again.", "fill": "#ffffff", "stroke": "#000000", "strokeWidth": 1, "key": -7, "refs": [], "ctsx": [], "comment": "null"}], "linkDataArray": [{"category": "ConsistsOf", "text": "consists of", "routing": {"yb": "Normal", "oE": 1}, "from": -1, "to": -2, "refs": [], "ctsx": [], "comment": "null"}, {"category": "ConsistsOf", "text": "consists of", "routing": {"yb": "Normal", "oE": 1}, "from": -1, "to": -3, "refs": [], "ctsx": [], "comment": "null"}, {"category": "ConsistsOf", "text": "consists of", "routing": {"yb": "Normal", "oE": 1}, "from": -1, "to": -4, "refs": [], "ctsx": [], "comment": "null"}, {"category": "ConsistsOf", "text": "consists of", "routing": {"yb": "Normal", "oE": 1}, "from": -1, "to": -5, "refs": [], "ctsx": [], "comment": "null"}, {"category": "ConsistsOf", "text": "consists of", "routing": {"yb": "Normal", "oE": 1}, "from": -1, "to": -6, "refs": [], "ctsx": [], "comment": "null"}, {"category": "ConsistsOf", "text": "consists of", "routing": {"yb": "Normal", "oE": 1}, "from": -1, "to": -7, "refs": [], "ctsx": [], "comment": "null"}]}