{"class": "go.GraphLinksModel", "nodeDataArray": [{"category": "Task", "text": "How to Convince Someone to Use DuckDuckGo", "fill": "#ffffff", "stroke": "#000000", "strokeWidth": 1, "key": -1, "refs": [], "ctsx": [], "comment": null}, {"category": "Task", "text": "Examine your own motives.", "fill": "#ffffff", "stroke": "#000000", "strokeWidth": 1, "key": -2, "refs": [], "ctsx": [], "comment": "null"}, {"category": "Task", "text": "Read up on how to Practice Nonviolent Communication. Practice Nonviolent Communication", "fill": "#ffffff", "stroke": "#000000", "strokeWidth": 1, "key": -3, "refs": [], "ctsx": [], "comment": "null"}, {"category": "Task", "text": "State your observation.", "fill": "#ffffff", "stroke": "#000000", "strokeWidth": 1, "key": -4, "refs": [], "ctsx": [], "comment": "null"}, {"category": "Task", "text": "State your feelings.", "fill": "#ffffff", "stroke": "#000000", "strokeWidth": 1, "key": -5, "refs": [], "ctsx": [], "comment": "null"}, {"category": "Task", "text": "State your need.", "fill": "#ffffff", "stroke": "#000000", "strokeWidth": 1, "key": -6, "refs": [], "ctsx": [], "comment": "null"}, {"category": "Task", "text": "Make a request.", "fill": "#ffffff", "stroke": "#000000", "strokeWidth": 1, "key": -7, "refs": [], "ctsx": [], "comment": "null"}, {"category": "Task", "text": "Remember that no means no.", "fill": "#ffffff", "stroke": "#000000", "strokeWidth": 1, "key": -8, "refs": [], "ctsx": [], "comment": "null"}], "linkDataArray": [{"category": "ConsistsOf", "text": "consists of", "routing": {"yb": "Normal", "oE": 1}, "from": -1, "to": -2, "refs": [], "ctsx": [], "comment": "null"}, {"category": "ConsistsOf", "text": "consists of", "routing": {"yb": "Normal", "oE": 1}, "from": -1, "to": -3, "refs": [], "ctsx": [], "comment": "null"}, {"category": "ConsistsOf", "text": "consists of", "routing": {"yb": "Normal", "oE": 1}, "from": -1, "to": -4, "refs": [], "ctsx": [], "comment": "null"}, {"category": "ConsistsOf", "text": "consists of", "routing": {"yb": "Normal", "oE": 1}, "from": -1, "to": -5, "refs": [], "ctsx": [], "comment": "null"}, {"category": "ConsistsOf", "text": "consists of", "routing": {"yb": "Normal", "oE": 1}, "from": -1, "to": -6, "refs": [], "ctsx": [], "comment": "null"}, {"category": "ConsistsOf", "text": "consists of", "routing": {"yb": "Normal", "oE": 1}, "from": -1, "to": -7, "refs": [], "ctsx": [], "comment": "null"}, {"category": "ConsistsOf", "text": "consists of", "routing": {"yb": "Normal", "oE": 1}, "from": -1, "to": -8, "refs": [], "ctsx": [], "comment": "null"}]}